Metadata-Version: 2.1
Name: simplearraysumVT
Version: 0.1.0
Summary: Calculate the sum of array
Home-page: https://github.com/VankaTaganai/simplearraysumVT
Author: Ivan Panov
Author-email: panovivan01@yandex.ru
License: UNKNOWN
Platform: UNKNOWN
